{
  "id": "spiral_matrix_26074_20260703_143846",
  "algorithm": "spiral_matrix",
  "period": "26074",
  "draw_date": "2026-07-04",
  "created_at": "2026-07-03 14:38:46",
  "status": "completed",
  "models_used": [
    "frequency",
    "poisson",
    "exponential_smoothing",
    "monte_carlo"
  ],
  "recommendations": [
    {
      "group": 1,
      "main": [
        6,
        13,
        15,
        18,
        26
      ],
      "sub": [
        2,
        9
      ],
      "score": 33.9,
      "reason": "🔥热号轮转: 衰减加权前12码->旋转矩阵(4-if-5)优选"
    },
    {
      "group": 2,
      "main": [
        3,
        11,
        13,
        15,
        26
      ],
      "sub": [
        1,
        6
      ],
      "score": 34.4,
      "reason": "📈趋势轮转: 近期窗口+上期邻域->旋转矩阵优选"
    },
    {
      "group": 3,
      "main": [
        7,
        16,
        17,
        19,
        24
      ],
      "sub": [
        6,
        9
      ],
      "score": 38.9,
      "reason": "❄️冷号轮转: 低频后14码->旋转矩阵优选"
    },
    {
      "group": 4,
      "main": [
        2,
        12,
        13,
        14,
        26
      ],
      "sub": [
        5,
        8
      ],
      "score": 30.1,
      "reason": "🔗邻域轮转: 上期号码+邻域补全->旋转矩阵优选"
    },
    {
      "group": 5,
      "main": [
        9,
        15,
        18,
        20,
        28
      ],
      "sub": [
        10,
        11
      ],
      "score": 41.4,
      "reason": "⚖️平衡轮转: 避开极端冷热,中间14码->旋转矩阵优选"
    }
  ],
  "actual_draw": {
    "main": [
      1,
      4,
      10,
      23,
      25
    ],
    "sub": [
      1,
      12
    ]
  },
  "matches": [
    {
      "group": 1,
      "main_matches": [],
      "sub_matches": [],
      "main_hits": 0,
      "sub_hits": 0,
      "total_hits": 0
    },
    {
      "group": 2,
      "main_matches": [],
      "sub_matches": [
        1
      ],
      "main_hits": 0,
      "sub_hits": 1,
      "total_hits": 1
    },
    {
      "group": 3,
      "main_matches": [],
      "sub_matches": [],
      "main_hits": 0,
      "sub_hits": 0,
      "total_hits": 0
    },
    {
      "group": 4,
      "main_matches": [],
      "sub_matches": [],
      "main_hits": 0,
      "sub_hits": 0,
      "total_hits": 0
    },
    {
      "group": 5,
      "main_matches": [],
      "sub_matches": [],
      "main_hits": 0,
      "sub_hits": 0,
      "total_hits": 0
    }
  ],
  "summary": {
    "actual_main": [
      1,
      4,
      10,
      23,
      25
    ],
    "actual_sub": [
      1,
      12
    ],
    "best_group": 2,
    "best_hits": 1,
    "avg_main_hits": 0.0,
    "avg_sub_hits": 0.2,
    "avg_total_hits": 0.2
  }
}